[
  {
    "id": "1",
    "name": "ALGS Overall Winner",
    "title": "Respawn",
    "description":"Winner Game 1 – (Ex)EUnited , Game 2 – TSM, Game 3 – Sola Fide, Game 4 – TSM, Game 5 – TSM",
    "image": "https://www.ggrecon.com/media/images/admin/apex-legends/algseu-overallpng.webp"
  },
  {
    "id": "2",
    "name": "ALGS Match 2 Server America",
    "title": "Respawn",
    "description":"Winner Game 1 – Alliance, Game 2 – Wygers, Game 3 – Alliance, Game 4 – CrowCrowd, Game 5 – Triumph",
    "image": "https://www.ggrecon.com/media/images/admin/apex-legends/algs-overall-winnerspng.webp"
  }
]